excel_af/__init__.py
excel_af/cell.py
excel_af/cell_checker.py
excel_af/column.py
excel_af/custom_sheet.py
excel_af/direction.py
excel_af/helpers.py
excel_af/row.py
excel_af/table.py
excel_af-0.0.5.dist-info/LICENSE
excel_af-0.0.5.dist-info/METADATA
excel_af-0.0.5.dist-info/WHEEL
excel_af-0.0.5.dist-info/top_level.txt
excel_af-0.0.5.dist-info/RECORD
