Metadata-Version: 2.1
Name: excel-af
Version: 0.0.5
Summary: Python package to work with Microsoft Excel files.
Home-page: https://github.com/AlbertFarhutdinov/excel_af
Author: Albert Farkhutdinov
Author-email: albertfarhutdinov@gmail.com
Classifier: Development Status :: 3 - Alpha
Classifier: Programming Language :: Python :: 3.9
Classifier: License :: OSI Approved :: GNU General Public License v3 (GPLv3)
Classifier: Operating System :: Microsoft :: Windows :: Windows 10
Requires-Python: >=3.6
License-File: LICENSE
Requires-Dist: xlwings (>=0.27.11)
Requires-Dist: pretty-repr (>=1.0.4)
Requires-Dist: math-round-af (>=1.0.3)
